{
  "2": {
    "id": "2",
    "sayi": 2,
    "yazarId": "533727549625204747",
    "icerik": "a",
    "medyaUrl": "https://cdn.discordapp.com/attachments/1329560487175917701/1370674071448059954/IMG_4875.gif?ex=68205b34&is=681f09b4&hm=70f473f0c07c585cbfac98dca55d9ba4b66dacd0e81ea7728545885b34c67392&",
    "olusturmaTarihi": "2025-05-10T08:09:24.741Z",
    "begeniSayisi": 0,
    "begenenler": [],
    "yorumlar": [
      {
        "yazarId": "533727549625204747",
        "icerik": "aaa",
        "olusturmaTarihi": "2025-05-12T11:25:16.958Z"
      }
    ]
  },
  "3": {
    "id": "3",
    "sayi": 3,
    "yazarId": "533727549625204747",
    "icerik": null,
    "medyaUrl": "https://cdn.discordapp.com/attachments/1329560487175917701/1370674173109731432/IMG_4875.gif?ex=68205b4c&is=681f09cc&hm=e0d10daf18761e7bf33a1112b1a78db433192d44588fe3b511bbcd56f8a9fed7&",
    "olusturmaTarihi": "2025-05-10T08:09:48.941Z",
    "begeniSayisi": 0,
    "begenenler": [],
    "yorumlar": [
      {
        "yazarId": "533727549625204747",
        "icerik": "123",
        "olusturmaTarihi": "2025-05-12T11:27:22.246Z"
      }
    ]
  },
  "4": {
    "id": "4",
    "sayi": 4,
    "yazarId": "533727549625204747",
    "icerik": null,
    "medyaUrl": "https://cdn.discordapp.com/attachments/1329560487175917701/1370675611718123561/IMG_4830.gif?ex=68205ca3&is=681f0b23&hm=b2de8732aee200b295dac06ab2967a210b2b629bc6119ef195296f1fb2dcf337&",
    "olusturmaTarihi": "2025-05-10T08:15:31.976Z",
    "begeniSayisi": 3,
    "begenenler": [
      "1305279380079120498",
      "1264702506684911667",
      "603605988804788423"
    ],
    "yorumlar": [
      {
        "yazarId": "533727549625204747",
        "icerik": "Aaaa",
        "olusturmaTarihi": "2025-05-12T11:23:39.467Z"
      }
    ]
  },
  "5": {
    "id": "5",
    "sayi": 5,
    "yazarId": "533727549625204747",
    "icerik": "a",
    "medyaUrl": null,
    "olusturmaTarihi": "2025-05-10T08:20:50.145Z",
    "begeniSayisi": 2,
    "begenenler": [
      "1264702506684911667",
      "603605988804788423"
    ],
    "yorumlar": []
  },
  "6": {
    "id": "6",
    "sayi": 6,
    "yazarId": "533727549625204747",
    "icerik": "a",
    "medyaUrl": null,
    "olusturmaTarihi": "2025-05-12T11:13:49.557Z",
    "begeniSayisi": 4,
    "begenenler": [
      "1264702506684911667",
      "1218816421165928448",
      "1190924668534800466",
      "564468317977575443"
    ],
    "yorumlar": [
      {
        "yazarId": "533727549625204747",
        "icerik": "Aa",
        "olusturmaTarihi": "2025-05-12T11:17:48.239Z"
      }
    ]
  },
  "7": {
    "id": "7",
    "sayi": 7,
    "yazarId": "533727549625204747",
    "icerik": "1",
    "medyaUrl": null,
    "olusturmaTarihi": "2025-05-12T11:36:37.728Z",
    "begeniSayisi": 3,
    "begenenler": [
      "1264702506684911667",
      "1097840178564972665",
      "1305279380079120498"
    ],
    "yorumlar": [
      {
        "yazarId": "533727549625204747",
        "icerik": "891",
        "olusturmaTarihi": "2025-05-12T11:36:49.882Z"
      }
    ],
    "mesajId": "1371450995912998975",
    "kanalId": "1329560487175917701"
  },
  "8": {
    "id": "8",
    "sayi": 8,
    "yazarId": "533727549625204747",
    "icerik": "a",
    "medyaUrl": null,
    "olusturmaTarihi": "2025-05-12T11:44:45.461Z",
    "begeniSayisi": 0,
    "begenenler": [],
    "yorumlar": [],
    "mesajId": "1371453041903009963",
    "kanalId": "1329560487175917701"
  },
  "9": {
    "id": "9",
    "sayi": 9,
    "yazarId": "533727549625204747",
    "icerik": "5",
    "medyaUrl": null,
    "olusturmaTarihi": "2025-05-12T11:46:38.024Z",
    "begeniSayisi": 3,
    "begenenler": [
      "1305279380079120498",
      "1264702506684911667",
      "564468317977575443"
    ],
    "yorumlar": [],
    "mesajId": "1371453513791569921",
    "kanalId": "1329560487175917701"
  },
  "10": {
    "id": "10",
    "sayi": 10,
    "yazarId": "533727549625204747",
    "icerik": null,
    "medyaUrl": "https://cdn.discordapp.com/attachments/1329560487175917701/1371454291520262155/generated_image.png?ex=682331d7&is=6821e057&hm=e25e04e291d806737b3f3e5b19c1e9d2b18dfab59779d2f5aeeba1d2c2fa96c0&",
    "olusturmaTarihi": "2025-05-12T11:49:43.719Z",
    "begeniSayisi": 0,
    "begenenler": [],
    "yorumlar": [],
    "mesajId": "1371454292791398461",
    "kanalId": "1329560487175917701"
  },
  "11": {
    "id": "11",
    "sayi": 11,
    "yazarId": "533727549625204747",
    "icerik": "1201",
    "medyaUrl": null,
    "olusturmaTarihi": "2025-05-12T11:51:33.226Z",
    "begeniSayisi": 0,
    "begenenler": [],
    "yorumlar": [],
    "mesajId": "1371454752197578753",
    "kanalId": "1329560487175917701"
  },
  "12": {
    "id": "12",
    "sayi": 12,
    "yazarId": "533727549625204747",
    "icerik": "a",
    "medyaUrl": null,
    "olusturmaTarihi": "2025-05-12T11:55:59.025Z",
    "begeniSayisi": 0,
    "begenenler": [],
    "yorumlar": [],
    "mesajId": "1371455867127468133",
    "kanalId": "1329560487175917701"
  },
  "13": {
    "id": "13",
    "sayi": 13,
    "yazarId": "533727549625204747",
    "icerik": "-",
    "medyaUrl": null,
    "olusturmaTarihi": "2025-05-12T12:07:13.698Z",
    "begeniSayisi": 1,
    "begenenler": [
      "533727549625204747"
    ],
    "yorumlar": [],
    "mesajId": "1371458696885960706",
    "kanalId": "1329560487175917701"
  },
  "14": {
    "id": "14",
    "sayi": 14,
    "yazarId": "533727549625204747",
    "icerik": "10",
    "medyaUrl": null,
    "olusturmaTarihi": "2025-05-12T12:11:21.230Z",
    "begeniSayisi": 4,
    "begenenler": [
      "533727549625204747",
      "1264702506684911667",
      "1254761985367871498",
      "1305279380079120498"
    ],
    "yorumlar": [],
    "mesajId": "1371459734858895372",
    "kanalId": "1329560487175917701"
  },
  "15": {
    "id": "15",
    "sayi": 15,
    "yazarId": "533727549625204747",
    "icerik": "z",
    "medyaUrl": null,
    "olusturmaTarihi": "2025-05-12T12:12:43.187Z",
    "begeniSayisi": 4,
    "begenenler": [
      "533727549625204747",
      "1264702506684911667",
      "1254761985367871498",
      "1305279380079120498"
    ],
    "yorumlar": [],
    "mesajId": "1371460078422720524",
    "kanalId": "1329560487175917701"
  },
  "16": {
    "id": "16",
    "sayi": 16,
    "yazarId": "533727549625204747",
    "icerik": null,
    "medyaUrl": "https://cdn.discordapp.com/attachments/1329560487175917701/1371797257791475763/giphy.mov?ex=68247141&is=68231fc1&hm=d201415f1905816793e8a91f915355cd2fcb85142859d0110729b5c0696bcb81&",
    "olusturmaTarihi": "2025-05-13T10:32:33.325Z",
    "begeniSayisi": 2,
    "begenenler": [
      "533727549625204747",
      "1264702506684911667"
    ],
    "yorumlar": [
      {
        "yazarId": "533727549625204747",
        "icerik": "OÇÇÇÇÇ",
        "olusturmaTarihi": "2025-05-13T10:32:47.290Z"
      }
    ],
    "mesajId": "1371797259557146696",
    "kanalId": "1329560487175917701"
  },
  "17": {
    "id": "17",
    "sayi": 17,
    "yazarId": "564468317977575443",
    "icerik": null,
    "medyaUrl": "https://cdn.discordapp.com/attachments/1329560487175917701/1371798120048103474/af41e4badf556be23acd146659738818.jpg?ex=6824720e&is=6823208e&hm=8752646c1ca036bbad4c82ddae197f324596037ad586bd51f644838ff2eb09f2&",
    "olusturmaTarihi": "2025-05-13T10:35:58.927Z",
    "begeniSayisi": 0,
    "begenenler": [],
    "yorumlar": [],
    "mesajId": "1371798121700524094",
    "kanalId": "1329560487175917701"
  },
  "18": {
    "id": "18",
    "sayi": 18,
    "yazarId": "564468317977575443",
    "icerik": "diyoz ya",
    "medyaUrl": null,
    "olusturmaTarihi": "2025-05-13T10:36:53.038Z",
    "begeniSayisi": 1,
    "begenenler": [
      "1254761985367871498"
    ],
    "yorumlar": [],
    "mesajId": "1371798349052641302",
    "kanalId": "1329560487175917701"
  },
  "19": {
    "id": "19",
    "sayi": 19,
    "yazarId": "564468317977575443",
    "icerik": "am sikici",
    "medyaUrl": "https://cdn.discordapp.com/attachments/1329560487175917701/1371798504787415070/5ae0623cc714bcae663797d9cec2db3a.jpg?ex=6824726a&is=682320ea&hm=bc76c7be3da05421b2c6e79b50611361fbca2097229bb3a1f46f85a5c51b9c36&",
    "olusturmaTarihi": "2025-05-13T10:37:30.728Z",
    "begeniSayisi": 0,
    "begenenler": [],
    "yorumlar": [],
    "mesajId": "1371798506523590769",
    "kanalId": "1329560487175917701"
  },
  "20": {
    "id": "20",
    "sayi": 20,
    "yazarId": "533727549625204747",
    "icerik": null,
    "medyaUrl": "https://cdn.discordapp.com/attachments/1329560487175917701/1371798782206939147/IMG_4873.gif?ex=682472ac&is=6823212c&hm=6dcb37d64c2a2f8e323d4344eb158aae0cf6d4ca612c8c268a0c089cf28d6fbf&",
    "olusturmaTarihi": "2025-05-13T10:38:36.794Z",
    "begeniSayisi": 0,
    "begenenler": [],
    "yorumlar": [
      {
        "yazarId": "533727549625204747",
        "icerik": "ÇOK İYİ",
        "olusturmaTarihi": "2025-05-13T10:39:42.404Z"
      }
    ],
    "mesajId": "1371798783628935230",
    "kanalId": "1330632714763763833"
  },
  "21": {
    "id": "21",
    "sayi": 21,
    "yazarId": "533727549625204747",
    "icerik": null,
    "medyaUrl": "https://cdn.discordapp.com/attachments/1329560487175917701/1371802620884287538/klausredd.mov?ex=6824763f&is=682324bf&hm=686c578404ec915e14b4477ac6725b2bf9024750e419509cf92e2e144f2a739f&",
    "olusturmaTarihi": "2025-05-13T10:53:51.979Z",
    "begeniSayisi": 0,
    "begenenler": [],
    "yorumlar": [],
    "mesajId": "1371802622104834059",
    "kanalId": "1330632714763763833"
  },
  "22": {
    "id": "22",
    "sayi": 22,
    "yazarId": "533727549625204747",
    "icerik": "a",
    "medyaUrl": null,
    "olusturmaTarihi": "2025-05-13T11:44:53.630Z",
    "begeniSayisi": 0,
    "begenenler": [],
    "yorumlar": [],
    "mesajId": "1371815463578767524",
    "kanalId": "1329560487175917701"
  },
  "23": {
    "id": "23",
    "sayi": 23,
    "yazarId": "533727549625204747",
    "icerik": null,
    "medyaUrl": "https://cdn.discordapp.com/attachments/1329560487175917701/1371815512597594243/giphy.mov?ex=68248241&is=682330c1&hm=c728ed471f7a59d6e42b4343700696aee7476547089ff4963a9bd5a010e056bd&",
    "olusturmaTarihi": "2025-05-13T11:45:05.446Z",
    "begeniSayisi": 0,
    "begenenler": [],
    "yorumlar": [],
    "mesajId": "1371815515034488833",
    "kanalId": "1329560487175917701"
  },
  "24": {
    "id": "24",
    "sayi": 24,
    "yazarId": "533727549625204747",
    "icerik": null,
    "medyaUrl": "https://cdn.discordapp.com/attachments/1329560487175917701/1371815698552324106/IMG_4873.gif?ex=6824826d&is=682330ed&hm=6b1171b9b22b6aa854e658604900b071fb1f00206da42bdda0fbe20cee749544&",
    "olusturmaTarihi": "2025-05-13T11:45:50.129Z",
    "begeniSayisi": 0,
    "begenenler": [],
    "yorumlar": [],
    "mesajId": "1371815701836333176",
    "kanalId": "1329560487175917701"
  },
  "25": {
    "id": "25",
    "sayi": 25,
    "yazarId": "533727549625204747",
    "icerik": null,
    "medyaUrl": "https://cdn.discordapp.com/attachments/1329560487175917701/1371815849798799490/IMG_4730.gif?ex=68248291&is=68233111&hm=8d6755c38f4ff1be859a527999de01788eff07d3642f57267dda680d01c084e8&",
    "olusturmaTarihi": "2025-05-13T11:46:25.916Z",
    "begeniSayisi": 0,
    "begenenler": [],
    "yorumlar": [],
    "mesajId": "1371815853753896960",
    "kanalId": "1329560487175917701"
  },
  "26": {
    "id": "26",
    "sayi": 26,
    "yazarId": "533727549625204747",
    "icerik": null,
    "medyaUrl": "https://cdn.discordapp.com/attachments/1329560487175917701/1371816117470887936/IMG_4900.png?ex=682482d1&is=68233151&hm=3cd06c4874c148de378e7a5a9bc201db1504293b95d399655d459f6b234f255c&",
    "olusturmaTarihi": "2025-05-13T11:47:29.726Z",
    "begeniSayisi": 0,
    "begenenler": [],
    "yorumlar": [],
    "mesajId": "1371816118934700074",
    "kanalId": "1329560487175917701"
  },
  "27": {
    "id": "27",
    "sayi": 27,
    "yazarId": "533727549625204747",
    "icerik": null,
    "medyaUrl": "https://cdn.discordapp.com/attachments/1329560487175917701/1371817151509434420/IMG_4749.jpg?ex=682483c8&is=68233248&hm=cd40179d2f1ee05287229f61b372bfc3d2c44cf3c93bace226aabd2f0db24d53&",
    "olusturmaTarihi": "2025-05-13T11:51:36.333Z",
    "begeniSayisi": 0,
    "begenenler": [],
    "yorumlar": [],
    "mesajId": "1371817152923041823",
    "kanalId": "1329560487175917701"
  },
  "28": {
    "id": "28",
    "sayi": 28,
    "yazarId": "533727549625204747",
    "icerik": null,
    "medyaUrl": "https://cdn.discordapp.com/attachments/1329560487175917701/1371817205515423775/giphy.mov?ex=682483d4&is=68233254&hm=0980f80f036bdef2db0a5f021c7bbe438419f8c6a98f7e56bd1893fb23b75ac2&",
    "olusturmaTarihi": "2025-05-13T11:51:49.071Z",
    "begeniSayisi": 0,
    "begenenler": [],
    "yorumlar": [],
    "mesajId": "1371817206442102845",
    "kanalId": "1329560487175917701"
  },
  "29": {
    "id": "29",
    "sayi": 29,
    "yazarId": "533727549625204747",
    "icerik": null,
    "medyaUrl": "https://cdn.discordapp.com/attachments/1329560487175917701/1371818650750947328/generated_image.png?ex=6824852d&is=682333ad&hm=02fec6d17ee0f36d55e1c5e04fa4965eba1618cd0340c78a9ab85d369576cf38&",
    "olusturmaTarihi": "2025-05-13T11:57:33.926Z",
    "begeniSayisi": 0,
    "begenenler": [],
    "yorumlar": [],
    "mesajId": "1371818653603074069",
    "kanalId": "1329560487175917701"
  },
  "30": {
    "id": "30",
    "sayi": 30,
    "yazarId": "533727549625204747",
    "icerik": null,
    "medyaUrl": "https://cdn.discordapp.com/attachments/1329560487175917701/1371818733613355091/giphy.mov?ex=68248541&is=682333c1&hm=1bea198b17e001192c43d023ecf592dd21ef33825af73ae038f9e72133454d88&",
    "olusturmaTarihi": "2025-05-13T11:57:53.432Z",
    "begeniSayisi": 2,
    "begenenler": [
      "603605988804788423",
      "533727549625204747"
    ],
    "yorumlar": [],
    "mesajId": "1371818736180400178",
    "kanalId": "1329560487175917701"
  },
  "31": {
    "id": "31",
    "sayi": 31,
    "yazarId": "533727549625204747",
    "icerik": null,
    "medyaUrl": "https://cdn.discordapp.com/attachments/1329560487175917701/1371819764963344394/giphy.mov?ex=68248637&is=682334b7&hm=a2e1dd0ac51d28e821ee873c211d08a1114b2e578ccfb734e0fe959f7b1fcb4a&",
    "olusturmaTarihi": "2025-05-13T12:01:59.347Z",
    "begeniSayisi": 0,
    "begenenler": [],
    "yorumlar": [],
    "mesajId": "1371819766746054709",
    "kanalId": "1329560487175917701"
  },
  "32": {
    "id": "32",
    "sayi": 32,
    "yazarId": "533727549625204747",
    "icerik": null,
    "medyaUrl": "https://cdn.discordapp.com/attachments/1329560487175917701/1371819821683048521/ban-hammer.gif?ex=68248644&is=682334c4&hm=b50af86d5f0111c7aa60a8fc35a2b59d1cc427744c43aab59658b403fe78067f&",
    "olusturmaTarihi": "2025-05-13T12:02:12.948Z",
    "begeniSayisi": 1,
    "begenenler": [
      "603605988804788423"
    ],
    "yorumlar": [],
    "mesajId": "1371819827576180777",
    "kanalId": "1329560487175917701"
  },
  "33": {
    "id": "33",
    "sayi": 33,
    "yazarId": "533727549625204747",
    "icerik": null,
    "medyaUrl": "https://cdn.discordapp.com/attachments/1329560487175917701/1371820755368546324/ban-hammer.gif?ex=68248723&is=682335a3&hm=3988c603f0f85bf40bb9a1256a4f003bd66e7bb13cc23e1a52afa3eb160c5f01&",
    "olusturmaTarihi": "2025-05-13T12:05:55.537Z",
    "begeniSayisi": 0,
    "begenenler": [],
    "yorumlar": [],
    "mesajId": "1371820761328783452",
    "kanalId": "1329560487175917701"
  },
  "34": {
    "id": "34",
    "sayi": 34,
    "yazarId": "533727549625204747",
    "icerik": null,
    "medyaUrl": "https://cdn.discordapp.com/attachments/1329560487175917701/1371822017715769344/ban-hammer.gif?ex=68248850&is=682336d0&hm=7cb157149e26368e4ffef450713f3fd3e3c7028a306527142da864de4ec34a17&",
    "olusturmaTarihi": "2025-05-13T12:10:56.436Z",
    "begeniSayisi": 0,
    "begenenler": [],
    "yorumlar": [],
    "mesajId": "1371822018831581214",
    "kanalId": "1329560487175917701"
  },
  "35": {
    "id": "35",
    "sayi": 35,
    "yazarId": "533727549625204747",
    "icerik": null,
    "medyaUrl": "https://cdn.discordapp.com/attachments/1329560487175917701/1371822076268384326/giphy.mov?ex=6824885e&is=682336de&hm=e7205d6d8af595d8e6f04b641520bf814ffb360fdea35673bb64de435b7fa442&",
    "olusturmaTarihi": "2025-05-13T12:11:10.428Z",
    "begeniSayisi": 0,
    "begenenler": [],
    "yorumlar": [],
    "mesajId": "1371822077547642941",
    "kanalId": "1329560487175917701"
  },
  "36": {
    "id": "36",
    "sayi": 36,
    "yazarId": "533727549625204747",
    "icerik": null,
    "medyaUrl": "https://cdn.discordapp.com/attachments/1329560487175917701/1371823213692321904/giphy.mov?ex=6824896d&is=682337ed&hm=82df5176b46fbad9a58cf1c2afd8eb9a0cd86ce1ecec5229977572263f5cf567&",
    "olusturmaTarihi": "2025-05-13T12:15:41.542Z",
    "begeniSayisi": 0,
    "begenenler": [],
    "yorumlar": [],
    "mesajId": "1371823214623457411",
    "kanalId": "1329560487175917701"
  },
  "37": {
    "id": "37",
    "sayi": 37,
    "yazarId": "533727549625204747",
    "icerik": null,
    "medyaUrl": "https://cdn.discordapp.com/attachments/1329560487175917701/1371823271070404658/ban-hammer.gif?ex=6824897b&is=682337fb&hm=842df5fac80deb896376f9c5d5a6a6d973fdccd2027eb0af2a8e4d4cfaf7a881&",
    "olusturmaTarihi": "2025-05-13T12:15:55.338Z",
    "begeniSayisi": 1,
    "begenenler": [
      "603605988804788423"
    ],
    "yorumlar": [],
    "mesajId": "1371823272471167127",
    "kanalId": "1329560487175917701"
  },
  "38": {
    "id": "38",
    "sayi": 38,
    "yazarId": "533727549625204747",
    "icerik": null,
    "medyaUrl": "https://cdn.discordapp.com/attachments/1329560487175917701/1371887064789946511/IMG_4471.jpg?ex=6824c4e4&is=68237364&hm=f168cbb2c5822561b61a5af9702dbf88a225db69611d7df7068a9a7734c72520&",
    "olusturmaTarihi": "2025-05-13T16:29:24.867Z",
    "begeniSayisi": 0,
    "begenenler": [],
    "yorumlar": [],
    "mesajId": "1371887065662226503",
    "kanalId": "1329560487175917701"
  },
  "39": {
    "id": "39",
    "sayi": 39,
    "yazarId": "533727549625204747",
    "icerik": "a",
    "medyaUrl": null,
    "olusturmaTarihi": "2025-05-13T16:40:56.327Z",
    "begeniSayisi": 0,
    "begenenler": [],
    "yorumlar": [],
    "mesajId": "1371889966128300112",
    "kanalId": "1329560487175917701"
  },
  "40": {
    "id": "40",
    "sayi": 40,
    "yazarId": "533727549625204747",
    "icerik": "a",
    "medyaUrl": null,
    "olusturmaTarihi": "2025-05-13T16:42:08.845Z",
    "begeniSayisi": 0,
    "begenenler": [],
    "yorumlar": [],
    "mesajId": "1371890270240505897",
    "kanalId": "1329560487175917701"
  },
  "41": {
    "id": "41",
    "sayi": 41,
    "yazarId": "533727549625204747",
    "icerik": "a",
    "medyaUrl": null,
    "olusturmaTarihi": "2025-05-13T16:43:20.726Z",
    "begeniSayisi": 0,
    "begenenler": [],
    "yorumlar": [],
    "mesajId": "1371890571689463962",
    "kanalId": "1329560487175917701"
  },
  "42": {
    "id": "42",
    "sayi": 42,
    "yazarId": "533727549625204747",
    "icerik": "a",
    "medyaUrl": null,
    "olusturmaTarihi": "2025-05-13T16:44:41.063Z",
    "begeniSayisi": 0,
    "begenenler": [],
    "yorumlar": [
      {
        "yazarId": "533727549625204747",
        "icerik": "a a a a a",
        "olusturmaTarihi": "2025-05-13T16:45:03.059Z"
      },
      {
        "yazarId": "533727549625204747",
        "icerik": "a",
        "olusturmaTarihi": "2025-05-13T16:53:47.305Z"
      },
      {
        "yazarId": "533727549625204747",
        "icerik": "a",
        "olusturmaTarihi": "2025-05-13T16:54:08.113Z"
      }
    ],
    "mesajId": "1371890909251375178",
    "kanalId": "1329560487175917701"
  },
  "43": {
    "id": "43",
    "sayi": 43,
    "yazarId": "533727549625204747",
    "icerik": "a",
    "medyaUrl": null,
    "olusturmaTarihi": "2025-05-13T17:06:06.059Z",
    "begeniSayisi": 0,
    "begenenler": [],
    "yorumlar": [],
    "mesajId": "1371896299082743908",
    "kanalId": "1330632714763763833"
  },
  "f8240f56-a88e-4fc7-8c6d-32913a015db1": {
    "id": "f8240f56-a88e-4fc7-8c6d-32913a015db1",
    "sayi": 1,
    "yazarId": "533727549625204747",
    "icerik": null,
    "medyaUrl": "https://cdn.discordapp.com/attachments/1329560487175917701/1370673413865078837/IMG_4873.gif?ex=68205a97&is=681f0917&hm=32e0e81da944de9589bbbbed683268a4a3f48d7e2e74f444c145d3942531476a&",
    "olusturmaTarihi": "2025-05-10T08:06:47.899Z",
    "begeniSayisi": 0,
    "begenenler": [],
    "yorumlar": []
  }
}